<?xml version = '1.0' encoding = 'UTF-8'?>
<Relation class="oracle.dbtools.crest.model.design.logical.Relation" name="Relation_5" directorySegmentName="seg_0" id="32C3351D-1A44-6977-FECF-375E4A25D334">
<createdBy>erick</createdBy>
<createdTime>2024-10-21 05:06:06 UTC</createdTime>
<ownerDesignName>Proyecto2</ownerDesignName>
<engineerTo>
<item key="1525BB72-52E6-AB1B-C3B2-3E6FA89A3596" value="true"/>
</engineerTo>
<sourcePk>2DACD0A0-4F90-7AEF-7770-E9A0C1F4D3FC</sourcePk>
<identifying>false</identifying>
<optionalSource>true</optionalSource>
<optionalTarget>false</optionalTarget>
<sourceCardinality>1</sourceCardinality>
<sourceEntity>B1399BD0-AB4D-6158-9728-E61F7F15BFBC</sourceEntity>
<targetCardinalityString>*</targetCardinalityString>
<targetEntity>A63451FF-4069-5170-8A48-7D070AFB5039</targetEntity>
<transferable>true</transferable>
<deleteRule>NO ACTION</deleteRule>
</Relation>
